{
  "$schema": "https://raw.githubusercontent.com/spdx/spdx-spec/v2.2.1/schemas/spdx-schema.json",
  "spdxVersion": "SPDX-2.2",
  "dataLicense": "CC0-1.0",
  "SPDXID": "SPDXRef-DOCUMENT",
  "documentNamespace": "https://spdx.org/spdxdocs/boost-system-x86-windows-1.82.0#2-3fd69888-a4e3-4aef-b371-16d332374664",
  "name": "boost-system:x86-windows@1.82.0#2 973c8056469808da0a955da2a45c9f230a928fbe46cd90aef2f2dd02853b2d4d",
  "creationInfo": {
    "creators": [
      "Tool: vcpkg-814b7ec837b59f1c8778f72351c1dd7605983cd2"
    ],
    "created": "2023-07-24T12:18:46Z"
  },
  "relationships": [
    {
      "spdxElementId": "SPDXRef-port",
      "relationshipType": "GENERATES",
      "relatedSpdxElement": "SPDXRef-binary"
    },
    {
      "spdxElementId": "SPDXRef-port",
      "relationshipType": "CONTAINS",
      "relatedSpdxElement": "SPDXRef-file-0"
    },
    {
      "spdxElementId": "SPDXRef-port",
      "relationshipType": "CONTAINS",
      "relatedSpdxElement": "SPDXRef-file-1"
    },
    {
      "spdxElementId": "SPDXRef-binary",
      "relationshipType": "GENERATED_FROM",
      "relatedSpdxElement": "SPDXRef-port"
    },
    {
      "spdxElementId": "SPDXRef-file-0",
      "relationshipType": "CONTAINED_BY",
      "relatedSpdxElement": "SPDXRef-port"
    },
    {
      "spdxElementId": "SPDXRef-file-1",
      "relationshipType": "CONTAINED_BY",
      "relatedSpdxElement": "SPDXRef-port"
    },
    {
      "spdxElementId": "SPDXRef-file-1",
      "relationshipType": "DEPENDENCY_MANIFEST_OF",
      "relatedSpdxElement": "SPDXRef-port"
    }
  ],
  "packages": [
    {
      "name": "boost-system",
      "SPDXID": "SPDXRef-port",
      "versionInfo": "1.82.0#2",
      "downloadLocation": "git+https://github.com/Microsoft/vcpkg#ports/boost-system",
      "homepage": "https://github.com/boostorg/system",
      "licenseConcluded": "BSL-1.0",
      "licenseDeclared": "NOASSERTION",
      "copyrightText": "NOASSERTION",
      "description": "Boost system module",
      "comment": "This is the port (recipe) consumed by vcpkg."
    },
    {
      "name": "boost-system:x86-windows",
      "SPDXID": "SPDXRef-binary",
      "versionInfo": "973c8056469808da0a955da2a45c9f230a928fbe46cd90aef2f2dd02853b2d4d",
      "downloadLocation": "NONE",
      "licenseConcluded": "BSL-1.0",
      "licenseDeclared": "NOASSERTION",
      "copyrightText": "NOASSERTION",
      "comment": "This is a binary package built by vcpkg."
    },
    {
      "SPDXID": "SPDXRef-resource-1",
      "name": "boostorg/system",
      "downloadLocation": "git+https://github.com/boostorg/system@boost-1.82.0",
      "licenseConcluded": "NOASSERTION",
      "licenseDeclared": "NOASSERTION",
      "copyrightText": "NOASSERTION",
      "checksums": [
        {
          "algorithm": "SHA512",
          "checksumValue": "96e2ef5cdc4886be3a8bd113ba542d5c633723761792758b510c6f99c751da1686fb099c32a1c684eace84c75a575bfa43859197e511cb8d3f678ff31c27dd66"
        }
      ]
    }
  ],
  "files": [
    {
      "fileName": "./portfile.cmake",
      "SPDXID": "SPDXRef-file-0",
      "checksums": [
        {
          "algorithm": "SHA256",
          "checksumValue": "8444bb5b468d94e557d89be337cd74490387d5f815737dde5ddda7948542522b"
        }
      ],
      "licenseConcluded": "NOASSERTION",
      "copyrightText": "NOASSERTION"
    },
    {
      "fileName": "./vcpkg.json",
      "SPDXID": "SPDXRef-file-1",
      "checksums": [
        {
          "algorithm": "SHA256",
          "checksumValue": "88d35abf56c5c8e928d0888bcf7d5c93cc8839fc8109f7a14aaf3652e788773c"
        }
      ],
      "licenseConcluded": "NOASSERTION",
      "copyrightText": "NOASSERTION"
    }
  ]
}
